tests/__init__.py
uncaught/__init__.py
uncaught/__main__.py
uncaught-0.0.1.dist-info/LICENSE
uncaught-0.0.1.dist-info/METADATA
uncaught-0.0.1.dist-info/WHEEL
uncaught-0.0.1.dist-info/entry_points.txt
uncaught-0.0.1.dist-info/top_level.txt
uncaught-0.0.1.dist-info/RECORD
